osipi/__init__.py
osipi/_aif.py
osipi-0.1.2.dist-info/LICENSE
osipi-0.1.2.dist-info/METADATA
osipi-0.1.2.dist-info/WHEEL
osipi-0.1.2.dist-info/top_level.txt
osipi-0.1.2.dist-info/RECORD
