Metadata-Version: 2.1
Name: osipi
Version: 0.1.2
Summary: The authorative python package for perfusion MRI
Author-email: Luis Torres <luistorres@flywheel.io>, Steven Sourbron <s.sourbron@sheffield.ac.uk>
License: Apache License
Project-URL: Homepage, https://osipi.github.io/pypi
Keywords: python,medical imaging,perfusion,MRI
Classifier: Development Status :: 3 - Alpha
Classifier: Intended Audience :: Developers
Classifier: Intended Audience :: Science/Research
Classifier: Topic :: Scientific/Engineering
Classifier: Operating System :: OS Independent
Classifier: License :: OSI Approved :: Apache Software License
Classifier: Programming Language :: Python
Classifier: Programming Language :: Python :: 3
Requires-Python: >=3.6
License-File: LICENSE
Requires-Dist: numpy
Provides-Extra: docs
Requires-Dist: sphinx ; extra == 'docs'
Requires-Dist: pydata-sphinx-theme ; extra == 'docs'
Requires-Dist: myst-parser ; extra == 'docs'
Requires-Dist: sphinx-copybutton ; extra == 'docs'
Requires-Dist: sphinx-design ; extra == 'docs'
Requires-Dist: sphinx-remove-toctrees ; extra == 'docs'
Requires-Dist: autodocsumm ; extra == 'docs'
Requires-Dist: docutils ; extra == 'docs'
Requires-Dist: sphinxcontrib-applehelp ; extra == 'docs'
Requires-Dist: sphinxcontrib-devhelp ; extra == 'docs'
Requires-Dist: sphinxcontrib-htmlhelp ; extra == 'docs'
Requires-Dist: sphinxcontrib-jsmath ; extra == 'docs'
Requires-Dist: sphinxcontrib-qthelp ; extra == 'docs'
Requires-Dist: sphinxcontrib-serializinghtml ; extra == 'docs'
Requires-Dist: sphinx-gallery ; extra == 'docs'
Provides-Extra: tests
Requires-Dist: pytest ; extra == 'tests'
Requires-Dist: matplotlib ; extra == 'tests'
